src/forward_pymodelscarp/__init__.py
src/forward_pymodelscarp/chemistry_scaling.py
src/forward_pymodelscarp/cl36_concentration.py
src/forward_pymodelscarp/constants.py
src/forward_pymodelscarp/forward_function.py
src/forward_pymodelscarp/geometric_scaling_factors.py
src/forward_pymodelscarp/parameters.py
src/forward_pymodelscarp/run_forward.py
src/forward_pymodelscarp/seismic_scenario.py
src/forward_pymodelscarp/util/__init__.py
src/forward_pymodelscarp/util/aicc.py
src/forward_pymodelscarp/util/geometric_scaling_functions.py
toto_scarp-0.0.3.dist-info/METADATA
toto_scarp-0.0.3.dist-info/WHEEL
toto_scarp-0.0.3.dist-info/licenses/LICENSE
toto_scarp-0.0.3.dist-info/RECORD
