Metadata-Version: 2.1
Name: toto_scarp
Version: 0.0.3
Summary: Forward function to generate chlorine 36 profiles on fault scarp
Author-email: Maureen Llinares <maureenllin@gmail.com>
License-File: LICENSE
Classifier: License :: OSI Approved :: MIT License
Classifier: Operating System :: OS Independent
Classifier: Programming Language :: Python :: 3
Requires-Python: >=3.9
